ConvDO/__init__.py
ConvDO/_operator_deprecated.py
ConvDO/boundaries.py
ConvDO/conv_operators.py
ConvDO/domain.py
ConvDO/faces.py
ConvDO/helpers.py
ConvDO/meta_type.py
ConvDO/obstacles.py
ConvDO/operations.py
ConvDO/schemes.py
ConvDO-0.1.0.dist-info/LICENSE
ConvDO-0.1.0.dist-info/METADATA
ConvDO-0.1.0.dist-info/WHEEL
ConvDO-0.1.0.dist-info/top_level.txt
ConvDO-0.1.0.dist-info/RECORD
