Metadata-Version: 2.1
Name: ConvDO
Version: 0.1.0
Summary: Convolutional Differential Operators with PyTorch
Home-page: https://qiauil.github.io/ConvDO/
Author: Qiauil
Author-email: qiangliu.7@outlook.com
Classifier: Programming Language :: Python :: 3
Classifier: License :: OSI Approved :: MIT License
Classifier: Operating System :: OS Independent
License-File: LICENSE
Requires-Dist: numpy
Requires-Dist: torch
